meshy_quantities-0.0.1.dist-info/DESCRIPTION.rst
meshy_quantities-0.0.1.dist-info/METADATA
meshy_quantities-0.0.1.dist-info/metadata.json
meshy_quantities-0.0.1.dist-info/RECORD
meshy_quantities-0.0.1.dist-info/top_level.txt
meshy_quantities-0.0.1.dist-info/WHEEL
quantities/__init__.py
quantities/length.py
