Metadata-Version: 2.0
Name: meshy-quantities
Version: 0.0.1
Summary: Represents and converts quantities of measurement.
Home-page: https://bitbucket.org/meshy/meshy-quantities
Author: Charlie Denton
Author-email: charlie@meshy.co.uk
License: MIT
Platform: UNKNOWN
Classifier: Development Status :: 1 - Planning
Classifier: Intended Audience :: Developers
Classifier: License :: OSI Approved :: MIT License
Classifier: Natural Language :: English
Classifier: Programming Language :: Python :: 3 :: Only
Classifier: Programming Language :: Python :: 3.4
Classifier: Topic :: Scientific/Engineering
Classifier: Topic :: Utilities
